accuralai_cache/__init__.py
accuralai_cache/base.py
accuralai_cache/disk.py
accuralai_cache/file.py
accuralai_cache/flexible_layered.py
accuralai_cache/layered.py
accuralai_cache/lfu.py
accuralai_cache/memory.py
accuralai_cache/noop.py
accuralai_cache/redis.py
accuralai_cache/ttl.py
accuralai_cache-0.2.1.dist-info/METADATA
accuralai_cache-0.2.1.dist-info/WHEEL
accuralai_cache-0.2.1.dist-info/entry_points.txt
accuralai_cache-0.2.1.dist-info/licenses/LICENSE
accuralai_cache-0.2.1.dist-info/RECORD
