Metadata-Version: 2.4
Name: accuralai-cache
Version: 0.2.1
Summary: Caching providers for the AccuralAI LLM pipeline.
Project-URL: homepage, https://accural-ai.web.app/
Project-URL: repository, https://github.com/AccuralAI/accuralai-cache
Project-URL: documentation, https://accuralai.readthedocs.io/en/latest/packages/accuralai-cache/index.html
Author: AccuralAI Maintainers
License: Apache-2.0
License-File: LICENSE
Requires-Python: >=3.10
Requires-Dist: accuralai-core
Requires-Dist: pydantic>=2.5
Provides-Extra: dev
Requires-Dist: pytest; extra == 'dev'
Requires-Dist: pytest-anyio; extra == 'dev'
Requires-Dist: pytest-mock; extra == 'dev'
Provides-Extra: redis
Requires-Dist: redis>=5.0; extra == 'redis'
